[
	{
		"__TYPE__": "SharedSliceContent",
		"variation": "default",
		"primary": {
			"content": {
				"__TYPE__": "StructuredTextContent",
				"value": [
					{
						"type": "paragraph",
						"content": {
							"text": "Nisi eiusmod nostrud laborum tempor adipisicing adipisicing proident sunt elit id. Excepteur commodo occaecat Lorem non fugiat laborum consequat occaecat sit."
						}
					}
				]
			},
			"sectionLabel": {
				"__TYPE__": "FieldContent",
				"value": "brain",
				"type": "Text"
			},
			"desktop_width": {
				"__TYPE__": "FieldContent",
				"value": "1/2",
				"type": "Select"
			},
			"slice_vertical_padding": {
				"__TYPE__": "FieldContent",
				"value": "0",
				"type": "Select"
			},
			"button_link": {
				"__TYPE__": "LinkContent",
				"value": {
					"__TYPE__": "ExternalLink",
					"url": "http://google.com"
				}
			},
			"button_text": {
				"__TYPE__": "FieldContent",
				"value": "lunch",
				"type": "Text"
			}
		},
		"items": [
			{
				"__TYPE__": "GroupItemContent",
				"value": []
			}
		]
	}
]